{
  "name": "ddlbx-theme-Dark+",
  "colors": {
    "activityBarBadge.background": "#eb444a",
    "sideBarTitle.foreground": "#00eeff",
    "activityBar.activeBorder": "#00eeff",
    "activityBar.background": "#32586b",
    "activityBar.foreground": "#00eeff",
    "activityBar.inactiveForeground": "#3f9afb",
    "titleBar.activeBackground": "#32586b"
  },
  "tokenColors": [
    {
      "name": "character",
      "scope": ["character"],
      "settings": {
        "foreground": "#C792EA"
      }
    },
    {
      "name": "type",
      "scope": ["type"],
      "settings": {
        "foreground": "#d1c10e"
      }
    },
    {
      "name": "expressions",
      "scope": ["expressions"],
      "settings": {
        "foreground": "#3f9afb"
      }
    },
    {
      "name": "identifier",
      "scope": ["identifier"],
      "settings": {
        "foreground": "#66D7D1"
      }
    },
    {
      "name": "keyword",
      "scope": ["keyword"],
      "settings": {
        "foreground": "#d1c10e"
      }
    },
    {
      "name": "keyword.operator",
      "scope": ["keyword.operator"],
      "settings": {
        "foreground": "#d1c10e"
      }
    },
    {
      "name": "keyword.operator.new",
      "scope": ["keyword.operator.new"],
      "settings": {
        "foreground": "#d1c10e"
      }
    },
    {
      "name": "keyword.operator.expression",
      "scope": ["keyword.operator.expression"],
      "settings": {
        "foreground": "#d1c10e"
      }
    },
    {
      "name": "keyword.operator.cast",
      "scope": ["keyword.operator.cast"],
      "settings": {
        "foreground": "#d1c10e"
      }
    },
    {
      "name": "keyword.operator.sizeof",
      "scope": ["keyword.operator.sizeof"],
      "settings": {
        "foreground": "#d1c10e"
      }
    },
    {
      "name": "keyword.operator.alignof",
      "scope": ["keyword.operator.alignof"],
      "settings": {
        "foreground": "#d1c10e"
      }
    },
    {
      "name": "keyword.operator.type",
      "scope": ["keyword.operator.type"],
      "settings": {
        "foreground": "#d1c10e"
      }
    },
    {
      "name": "keyword.operator.logical",
      "scope": ["keyword.operator.logical"],
      "settings": {
        "foreground": "#d1c10e"
      }
    },
    {
      "name": "keyword.operator.bitwise",
      "scope": ["keyword.operator.bitwise"],
      "settings": {
        "foreground": "#d1c10e"
      }
    },
    {
      "name": "keyword.operator.increment",
      "scope": ["keyword.operator.increment"],
      "settings": {
        "foreground": "#d1c10e"
      }
    },
    {
      "name": "keyword.operator.decrement",
      "scope": ["keyword.operator.decrement"],
      "settings": {
        "foreground": "#d1c10e"
      }
    },
    {
      "name": "keyword.operator.assignment",
      "scope": ["keyword.operator.assignment"]
    }
  ]
}
